{"count":20,"items":[{"id":"53f95852498ef3e7be057e84","createdAt":1408850002,"text":"PCB (Plan Check Burger) is awesome.","type":"user","canonicalUrl":"https:\/\/foursquare.com\/item\/53f95852498ef3e7be057e84","viewCount":42,"agreeCount":0,"disagreeCount":0,"user":{"id":"18423100","firstName":"Larry","lastName":"Vincent","gender":"male","relationship":"self","photo":{"prefix":"https:\/\/igx.4sqi.net\/img\/user\/","suffix":"\/18423100-LZ1DC0ASPDV2BAKH.jpg"}},"venue":{"id":"4f380f75e4b0d26ba1ab696f","name":"Plan Check Kitchen + Bar","url":"https:\/\/foursquare.com\/v\/plan-check-kitchen--bar\/4f380f75e4b0d26ba1ab696f"}},{"id":"530a95cf498e5c7a2aae3aa7","createdAt":1393202639,"text":"Bring cash. They don't take plastic.","type":"user","canonicalUrl":"https:\/\/foursquare.com\/item\/530a95cf498e5c7a2aae3aa7","viewCount":59,"agreeCount":0,"disagreeCount":0,"user":{"id":"18423100","firstName":"Larry","lastName":"Vincent","gender":"male","relationship":"self","photo":{"prefix":"https:\/\/igx.4sqi.net\/img\/user\/","suffix":"\/18423100-LZ1DC0ASPDV2BAKH.jpg"}},"venue":{"id":"4a413064f964a520f0a41fe3","name":"Hole in the Wall Burger Joint","url":"https:\/\/foursquare.com\/v\/hole-in-the-wall-burger-joint\/4a413064f964a520f0a41fe3"}},{"id":"52e579de498ed16db0df6378","createdAt":1390770654,"text":"Despite the fact that it has the ambience of a Marriott lobby bar, the food is quite good. Try the black cod.","type":"user","canonicalUrl":"https:\/\/foursquare.com\/item\/52e579de498ed16db0df6378","viewCount":52,"agreeCount":0,"disagreeCount":0,"user":{"id":"18423100","firstName":"Larry","lastName":"Vincent","gender":"male","relationship":"self","photo":{"prefix":"https:\/\/igx.4sqi.net\/img\/user\/","suffix":"\/18423100-LZ1DC0ASPDV2BAKH.jpg"}},"venue":{"id":"55020efb498e139cb469188b","name":"Blue Stove","url":"https:\/\/foursquare.com\/v\/blue-stove\/55020efb498e139cb469188b"}},{"id":"51d4a391498ea1498c9c7b82","createdAt":1372890001,"text":"If you've decided to go scruffy, they do awesome beard trimming here. Book it and rock the whiskers with style.","type":"user","canonicalUrl":"https:\/\/foursquare.com\/item\/51d4a391498ea1498c9c7b82","viewCount":149,"agreeCount":0,"disagreeCount":0,"user":{"id":"18423100","firstName":"Larry","lastName":"Vincent","gender":"male","relationship":"self","photo":{"prefix":"https:\/\/igx.4sqi.net\/img\/user\/","suffix":"\/18423100-LZ1DC0ASPDV2BAKH.jpg"}},"venue":{"id":"4eca69ed0cd617457309ba57","name":"The Art of Shaving","url":"https:\/\/foursquare.com\/v\/the-art-of-shaving\/4eca69ed0cd617457309ba57"}},{"id":"51b698d8498e47d69f9fcae4","createdAt":1370921176,"text":"I second the vote for the bacon-wrapped dates. Maybe the best thing I've ever put in my mouth!","type":"user","canonicalUrl":"https:\/\/foursquare.com\/item\/51b698d8498e47d69f9fcae4","viewCount":57,"agreeCount":0,"disagreeCount":0,"user":{"id":"18423100","firstName":"Larry","lastName":"Vincent","gender":"male","relationship":"self","photo":{"prefix":"https:\/\/igx.4sqi.net\/img\/user\/","suffix":"\/18423100-LZ1DC0ASPDV2BAKH.jpg"}},"venue":{"id":"4b594087f964a520038328e3","name":"Kinley's Restaurant & Bar","url":"https:\/\/foursquare.com\/v\/kinleys-restaurant--bar\/4b594087f964a520038328e3"}},{"id":"513ce295e4b0bfae27497445","createdAt":1362944661,"text":"You'll probably come for the beer, but their selection of bourbon, rye and other whiskeys is nothing short of awe-inspiring!","type":"user","canonicalUrl":"https:\/\/foursquare.com\/item\/513ce295e4b0bfae27497445","likes":{"count":2,"groups":[],"summary":"2 likes"},"viewCount":1122,"agreeCount":2,"disagreeCount":0,"user":{"id":"18423100","firstName":"Larry","lastName":"Vincent","gender":"male","relationship":"self","photo":{"prefix":"https:\/\/igx.4sqi.net\/img\/user\/","suffix":"\/18423100-LZ1DC0ASPDV2BAKH.jpg"}},"venue":{"id":"4f5d7583e4b0a3bd247a11d3","name":"The Blackheart","url":"https:\/\/foursquare.com\/v\/the-blackheart\/4f5d7583e4b0a3bd247a11d3"}},{"id":"504d6466e4b0838e313b6987","createdAt":1347249254,"text":"The burger is the crowd favorite, but check for some of the specials like the picnic style tuna sandwich or the excellent pulled pork.","type":"user","canonicalUrl":"https:\/\/foursquare.com\/item\/504d6466e4b0838e313b6987","viewCount":290,"agreeCount":0,"disagreeCount":0,"user":{"id":"18423100","firstName":"Larry","lastName":"Vincent","gender":"male","relationship":"self","photo":{"prefix":"https:\/\/igx.4sqi.net\/img\/user\/","suffix":"\/18423100-LZ1DC0ASPDV2BAKH.jpg"}},"venue":{"id":"4a4ea9c9f964a520e0ae1fe3","name":"R+D Kitchen","url":"https:\/\/foursquare.com\/v\/rd-kitchen\/4a4ea9c9f964a520e0ae1fe3"}},{"id":"50394a9ee4b0fad35da91667","createdAt":1345931934,"text":"Do yourself a favor. Start with the off-menu selections on the chalk board. I come here at least once a week and I have yet to be disappointed. The chef rocks here.","type":"user","canonicalUrl":"https:\/\/foursquare.com\/item\/50394a9ee4b0fad35da91667","likes":{"count":2,"groups":[],"summary":"2 likes"},"viewCount":870,"agreeCount":2,"disagreeCount":0,"user":{"id":"18423100","firstName":"Larry","lastName":"Vincent","gender":"male","relationship":"self","photo":{"prefix":"https:\/\/igx.4sqi.net\/img\/user\/","suffix":"\/18423100-LZ1DC0ASPDV2BAKH.jpg"}},"venue":{"id":"4ec71e384fc60d5801bd52a4","name":"Milo and Olive","url":"https:\/\/foursquare.com\/v\/milo-and-olive\/4ec71e384fc60d5801bd52a4"}},{"id":"4fde7c08e4b0ec5a8fad17e2","createdAt":1339980808,"text":"You have to love the ability to buy wasabi peas at the snack bar.","type":"user","canonicalUrl":"https:\/\/foursquare.com\/item\/4fde7c08e4b0ec5a8fad17e2","viewCount":146,"agreeCount":0,"disagreeCount":0,"user":{"id":"18423100","firstName":"Larry","lastName":"Vincent","gender":"male","relationship":"self","photo":{"prefix":"https:\/\/igx.4sqi.net\/img\/user\/","suffix":"\/18423100-LZ1DC0ASPDV2BAKH.jpg"}},"venue":{"id":"49fdfcfbf964a520546f1fe3","name":"Landmark Theatres","url":"https:\/\/foursquare.com\/v\/landmark-theatres\/49fdfcfbf964a520546f1fe3"}},{"id":"4f92d5eae4b0d0d98887fe57","createdAt":1335023082,"text":"Lots of people talk about how great the food is here. What they don't say is that the coffee is great and staff friendly. So order a cup and strike up a conversation!","type":"user","canonicalUrl":"https:\/\/foursquare.com\/item\/4f92d5eae4b0d0d98887fe57","viewCount":490,"agreeCount":0,"disagreeCount":0,"user":{"id":"18423100","firstName":"Larry","lastName":"Vincent","gender":"male","relationship":"self","photo":{"prefix":"https:\/\/igx.4sqi.net\/img\/user\/","suffix":"\/18423100-LZ1DC0ASPDV2BAKH.jpg"}},"venue":{"id":"4ec71e384fc60d5801bd52a4","name":"Milo and Olive","url":"https:\/\/foursquare.com\/v\/milo-and-olive\/4ec71e384fc60d5801bd52a4"}},{"id":"4f844eeae4b00dd9525b20f1","createdAt":1334071018,"text":"For breakfast, the house smoked salmon and scrambled eggs is quite good. The egg white frittata is a little odd.","type":"user","canonicalUrl":"https:\/\/foursquare.com\/item\/4f844eeae4b00dd9525b20f1","viewCount":256,"agreeCount":0,"disagreeCount":0,"user":{"id":"18423100","firstName":"Larry","lastName":"Vincent","gender":"male","relationship":"self","photo":{"prefix":"https:\/\/igx.4sqi.net\/img\/user\/","suffix":"\/18423100-LZ1DC0ASPDV2BAKH.jpg"}},"venue":{"id":"4f5977cae4b0a5edcff0d1f1","name":"Trace","url":"https:\/\/foursquare.com\/v\/trace\/4f5977cae4b0a5edcff0d1f1"}},{"id":"4f7f2930e4b0e160b8105af7","createdAt":1333733680,"text":"The French French Toast is the dish for those with a sweet tooth. But my favorite is the Huevos Normalita.","type":"user","canonicalUrl":"https:\/\/foursquare.com\/item\/4f7f2930e4b0e160b8105af7","likes":{"count":1,"groups":[],"summary":"1 like"},"viewCount":233,"agreeCount":1,"disagreeCount":0,"user":{"id":"18423100","firstName":"Larry","lastName":"Vincent","gender":"male","relationship":"self","photo":{"prefix":"https:\/\/igx.4sqi.net\/img\/user\/","suffix":"\/18423100-LZ1DC0ASPDV2BAKH.jpg"}},"venue":{"id":"3fd66200f964a52056ea1ee3","name":"Norma's","url":"https:\/\/foursquare.com\/v\/normas\/3fd66200f964a52056ea1ee3"}},{"id":"4f7b97a6e4b0f6b0d452aad7","createdAt":1333499814,"text":"If you don't try the lobster pappardelle you're an idiot. Five stars!","type":"user","canonicalUrl":"https:\/\/foursquare.com\/item\/4f7b97a6e4b0f6b0d452aad7","viewCount":69,"agreeCount":0,"disagreeCount":0,"user":{"id":"18423100","firstName":"Larry","lastName":"Vincent","gender":"male","relationship":"self","photo":{"prefix":"https:\/\/igx.4sqi.net\/img\/user\/","suffix":"\/18423100-LZ1DC0ASPDV2BAKH.jpg"}},"venue":{"id":"4bb7d7b898c7ef3b29763002","name":"The Modern","url":"https:\/\/foursquare.com\/v\/the-modern\/4bb7d7b898c7ef3b29763002"}},{"id":"4f773041e4b09a0a538a1a2a","createdAt":1333211201,"text":"I keep thinking there's nothing better than ___ dish, then come back to discover a new favorite. The roasted potatoes with sunny side eggs is my latest pick. Get it with the optional sausage.","type":"user","canonicalUrl":"https:\/\/foursquare.com\/item\/4f773041e4b09a0a538a1a2a","likes":{"count":1,"groups":[],"summary":"1 like"},"viewCount":616,"agreeCount":1,"disagreeCount":0,"user":{"id":"18423100","firstName":"Larry","lastName":"Vincent","gender":"male","relationship":"self","photo":{"prefix":"https:\/\/igx.4sqi.net\/img\/user\/","suffix":"\/18423100-LZ1DC0ASPDV2BAKH.jpg"}},"venue":{"id":"4ec71e384fc60d5801bd52a4","name":"Milo and Olive","url":"https:\/\/foursquare.com\/v\/milo-and-olive\/4ec71e384fc60d5801bd52a4"}},{"id":"4f75b288e4b0ae71abdae160","createdAt":1333113480,"text":"Use the text messaging service to know when your bus is coming. For the stop at 26th heading east, text 8383 to 41411","type":"user","canonicalUrl":"https:\/\/foursquare.com\/item\/4f75b288e4b0ae71abdae160","viewCount":399,"agreeCount":0,"disagreeCount":0,"user":{"id":"18423100","firstName":"Larry","lastName":"Vincent","gender":"male","relationship":"self","photo":{"prefix":"https:\/\/igx.4sqi.net\/img\/user\/","suffix":"\/18423100-LZ1DC0ASPDV2BAKH.jpg"}},"venue":{"id":"4e13bc46483bfda2e0a046c5","name":"Metro Bus 720","url":"https:\/\/foursquare.com\/v\/metro-bus-720\/4e13bc46483bfda2e0a046c5"}},{"id":"4f6e814ee4b0e0075ba1cd56","createdAt":1332642126,"text":"Hard to beat the chili relleno. It's all vegetarian. Except for massive amount of delicious cheese!","type":"user","canonicalUrl":"https:\/\/foursquare.com\/item\/4f6e814ee4b0e0075ba1cd56","viewCount":31,"agreeCount":0,"disagreeCount":0,"user":{"id":"18423100","firstName":"Larry","lastName":"Vincent","gender":"male","relationship":"self","photo":{"prefix":"https:\/\/igx.4sqi.net\/img\/user\/","suffix":"\/18423100-LZ1DC0ASPDV2BAKH.jpg"}},"venue":{"id":"4d8ce5ff830160fcdcb13d35","name":"Taberna Mexicana","url":"https:\/\/foursquare.com\/v\/taberna-mexicana\/4d8ce5ff830160fcdcb13d35"}},{"id":"4f6d519ce4b08d8da5b9a91a","createdAt":1332564380,"text":"This place is famous for its beef dip. And it lives up to its infamy.","type":"user","canonicalUrl":"https:\/\/foursquare.com\/item\/4f6d519ce4b08d8da5b9a91a","likes":{"count":1,"groups":[],"summary":"1 like"},"viewCount":376,"agreeCount":1,"disagreeCount":0,"user":{"id":"18423100","firstName":"Larry","lastName":"Vincent","gender":"male","relationship":"self","photo":{"prefix":"https:\/\/igx.4sqi.net\/img\/user\/","suffix":"\/18423100-LZ1DC0ASPDV2BAKH.jpg"}},"venue":{"id":"4bcbcfe9511f95213437b2c7","name":"South Beverly Grill","url":"https:\/\/foursquare.com\/v\/south-beverly-grill\/4bcbcfe9511f95213437b2c7"}},{"id":"4f581497e4b0bd50f6d34dfe","createdAt":1331172503,"text":"The marinated skirt steak on the happy hour menu is easily one of the best dishes they serve.","type":"user","canonicalUrl":"https:\/\/foursquare.com\/item\/4f581497e4b0bd50f6d34dfe","likes":{"count":1,"groups":[],"summary":"1 like"},"viewCount":540,"agreeCount":1,"disagreeCount":0,"user":{"id":"18423100","firstName":"Larry","lastName":"Vincent","gender":"male","relationship":"self","photo":{"prefix":"https:\/\/igx.4sqi.net\/img\/user\/","suffix":"\/18423100-LZ1DC0ASPDV2BAKH.jpg"}},"venue":{"id":"4ab99bfaf964a520028020e3","name":"Wilshire Restaurant","url":"https:\/\/foursquare.com\/v\/wilshire-restaurant\/4ab99bfaf964a520028020e3"}},{"id":"4f37f8afe4b02a70e1d1ee72","createdAt":1329068207,"text":"Get the mushroom grits for breakfast. Unbelievable savory goodness!","type":"user","canonicalUrl":"https:\/\/foursquare.com\/item\/4f37f8afe4b02a70e1d1ee72","viewCount":260,"agreeCount":0,"disagreeCount":0,"user":{"id":"18423100","firstName":"Larry","lastName":"Vincent","gender":"male","relationship":"self","photo":{"prefix":"https:\/\/igx.4sqi.net\/img\/user\/","suffix":"\/18423100-LZ1DC0ASPDV2BAKH.jpg"}},"venue":{"id":"4ec71e384fc60d5801bd52a4","name":"Milo and Olive","url":"https:\/\/foursquare.com\/v\/milo-and-olive\/4ec71e384fc60d5801bd52a4"}},{"id":"4f371f23e4b00af179b37dfe","createdAt":1329012515,"text":"The potato skins are spicy but good","type":"user","canonicalUrl":"https:\/\/foursquare.com\/item\/4f371f23e4b00af179b37dfe","viewCount":219,"agreeCount":0,"disagreeCount":0,"user":{"id":"18423100","firstName":"Larry","lastName":"Vincent","gender":"male","relationship":"self","photo":{"prefix":"https:\/\/igx.4sqi.net\/img\/user\/","suffix":"\/18423100-LZ1DC0ASPDV2BAKH.jpg"}},"venue":{"id":"4b479626f964a520813626e3","name":"Pacific Dining Car - Santa Monica","url":"https:\/\/foursquare.com\/v\/pacific-dining-car--santa-monica\/4b479626f964a520813626e3"}}]}